ranpasscli.py
app/__init__.py
app/__main__.py
app/application.py
RanPassCLI-0.0.1.dist-info/LICENSE
RanPassCLI-0.0.1.dist-info/METADATA
RanPassCLI-0.0.1.dist-info/WHEEL
RanPassCLI-0.0.1.dist-info/entry_points.txt
RanPassCLI-0.0.1.dist-info/top_level.txt
RanPassCLI-0.0.1.dist-info/RECORD
