Metadata-Version: 2.1
Name: RanPassCLI
Version: 0.0.1
Summary: Random password generator
Home-page: https://github.com/Damian-Sanchez/ranpasscli
Author: Damian Sanchez
Author-email: damiansanchez@onmail.com
License: MIT
Platform: UNKNOWN
Classifier: Programming Language :: Python :: 3.8
Classifier: License :: OSI Approved :: MIT License
Classifier: Operating System :: OS Independent
Requires-Python: >=3.7
Requires-Dist: click (>=8.0.1)
